{
  "users": [
    {
      "phone": "6285810287828",
      "username": "dhikzx",
      "pin": "dikz123"
    },
    {
      "phone": "6283152956289",
      "username": "noize",
      "pin": "1"
    },
    {
      "phone": "66640748309",
      "username": "dikz",
      "pin": "1"
    },
    {
      "phone": "6285824460752",
      "username": "bl",
      "pin": "tes"
    }
  ],
  "blacklist": [
    {
      "phone": "6285824460752",
      "username": "user_6285824460752",
      "reason": "Malink",
      "timestamp": "2025-05-09T18:22:15.780Z"
    }
  ]
}